PQLseqPy/PQLseqPy.py
PQLseqPy/__init__.py
pqlseqpy-0.1.2.dist-info/licenses/LICENSE
pqlseqpy-0.1.2.dist-info/METADATA
pqlseqpy-0.1.2.dist-info/WHEEL
pqlseqpy-0.1.2.dist-info/top_level.txt
pqlseqpy-0.1.2.dist-info/RECORD
