Metadata-Version: 2.4
Name: PQLseqPy
Version: 0.1.2
Summary: Fast PQLseq
Author-email: Ali Akbari <alek0991@gmail.com>
License: MIT License
Requires-Python: >=3.8
License-File: LICENSE
Requires-Dist: pandas
Requires-Dist: numpy
Requires-Dist: statsmodels
Requires-Dist: scipy
Dynamic: license-file
